README.txt
setup.cfg
setup.py
collective/__init__.py
collective.setuphelpers.egg-info/PKG-INFO
collective.setuphelpers.egg-info/SOURCES.txt
collective.setuphelpers.egg-info/dependency_links.txt
collective.setuphelpers.egg-info/entry_points.txt
collective.setuphelpers.egg-info/namespace_packages.txt
collective.setuphelpers.egg-info/not-zip-safe
collective.setuphelpers.egg-info/requires.txt
collective.setuphelpers.egg-info/top_level.txt
collective/setuphelpers/README.txt
collective/setuphelpers/__init__.py
collective/setuphelpers/configure.zcml
collective/setuphelpers/structure.py
collective/setuphelpers/tests.py
collective/setuphelpers/usersandgroups.py
collective/setuphelpers/utils.py
collective/setuphelpers/various.py
docs/HISTORY.txt
docs/INSTALL.txt
docs/LICENSE.GPL
docs/LICENSE.txt