Metadata-Version: 1.0
Name: collective.setuphelpers
Version: 0.6.1
Summary: Various simple functions to be used in Plone's setuphandlers
Home-page: http://www.fry-it.com
Author: Fry-IT
Author-email: matous@fry-it.com
License: GPL
Keywords: Plone setup setuphandlers
Platform: UNKNOWN
Classifier: Framework :: Plone
Classifier: Programming Language :: Python
